[
  { "year": 2009, "value": 11726886.26 },
  { "year": 2010, "value": 10759951.49 },
  { "year": 2011, "value": 19004454.83 },
  { "year": 2012, "value": 23349742.37 },
  { "year": 2013, "value": 24657062.52 },
  { "year": 2014, "value": 22519341.74 },
  { "year": 2015, "value": 28890498.27 },
  { "year": 2016, "value": 25301886.22 },
  { "year": 2017, "value": 26672743.26 },
  { "year": 2018, "value": 25598701.33 },
  { "year": 2019, "value": 25261616.38 },
  { "year": 2020, "value": 11037581.49 }
]
